restmachine/__init__.py
restmachine/_version.py
restmachine/adapters.py
restmachine/application.py
restmachine/content_renderers.py
restmachine/cors.py
restmachine/csp.py
restmachine/dependencies.py
restmachine/error_models.py
restmachine/exceptions.py
restmachine/metrics.py
restmachine/metrics_handler.py
restmachine/models.py
restmachine/router.py
restmachine/server.py
restmachine/servers.py
restmachine/state_machine.py
restmachine/streaming.py
restmachine/template_helpers.py
restmachine/testing/__init__.py
restmachine/testing/drivers.py
restmachine/testing/dsl.py
restmachine/testing/http_drivers.py
restmachine/testing/multi_driver_base.py
restmachine-0.1.1.dist-info/METADATA
restmachine-0.1.1.dist-info/WHEEL
restmachine-0.1.1.dist-info/top_level.txt
restmachine-0.1.1.dist-info/RECORD
