Metadata-Version: 2.4
Name: restmachine
Version: 0.1.1
Summary: A lightweight REST framework with dependency injection and webmachine-style state machine
Author-email: Ryan Festag <rfestag@gmail.com>
License: MIT
Project-URL: Homepage, https://github.com/rfestag/restmachine-python
Project-URL: Repository, https://github.com/rfestag/restmachine-python
Project-URL: Bug Reports, https://github.com/rfestag/restmachine-python/issues
Keywords: rest,api,framework,webmachine,state-machine,dependency-injection
Classifier: Development Status :: 3 - Alpha
Classifier: Intended Audience :: Developers
Classifier: Topic :: Software Development :: Libraries :: Python Modules
Classifier: Topic :: Internet :: WWW/HTTP :: HTTP Servers
Classifier: Programming Language :: Python :: 3
Classifier: Programming Language :: Python :: 3.9
Classifier: Programming Language :: Python :: 3.10
Classifier: Programming Language :: Python :: 3.11
Classifier: Programming Language :: Python :: 3.12
Classifier: Programming Language :: Python :: 3.13
Requires-Python: >=3.9
Requires-Dist: jinja2>=3.0.0
Requires-Dist: anyio>=3.0.0
Provides-Extra: validation
Requires-Dist: pydantic>=2.0.0; extra == "validation"
Provides-Extra: test
Requires-Dist: pytest>=6.0; extra == "test"
Requires-Dist: pytest-cov; extra == "test"
Requires-Dist: pytest-benchmark>=4.0.0; extra == "test"
Requires-Dist: requests>=2.25.0; extra == "test"
Requires-Dist: pydantic>=2.0.0; extra == "test"
Provides-Extra: dev
Requires-Dist: pytest>=6.0; extra == "dev"
Requires-Dist: pytest-cov; extra == "dev"
Requires-Dist: pytest-benchmark>=4.0.0; extra == "dev"
Requires-Dist: ruff; extra == "dev"
Requires-Dist: mypy; extra == "dev"
Requires-Dist: openapi-spec-validator>=0.7.0; extra == "dev"
Requires-Dist: requests>=2.25.0; extra == "dev"
Requires-Dist: pydantic>=2.0.0; extra == "dev"
Requires-Dist: genbadge[coverage]>=1.1.0; extra == "dev"
Requires-Dist: radon>=6.0.0; extra == "dev"
